dlex/__init__.py
dlex/base.py
dlex/colab.py
dlex/configs.py
dlex/datatypes.py
dlex/evaluate.py
dlex/export.py
dlex/infer.py
dlex/log.py
dlex/prepare.py
dlex/prepare_dataset.py
dlex/report.py
dlex/show.py
dlex/socket_utils.py
dlex/train.py
dlex/datasets/__init__.py
dlex/datasets/aliases.py
dlex/datasets/anki.py
dlex/datasets/base.py
dlex/datasets/builder.py
dlex/datasets/cornell_movie_dialogs_corpus.py
dlex/datasets/dummy.py
dlex/datasets/keras.py
dlex/datasets/sate.py
dlex/datasets/sklearn.py
dlex/datasets/squad.py
dlex/datasets/tf.py
dlex/datasets/torch.py
dlex/datasets/base/__init__.py
dlex/datasets/base/base.py
dlex/datasets/base/nlp.py
dlex/datasets/base/voice.py
dlex/datasets/image/__init__.py
dlex/datasets/image/builder.py
dlex/datasets/image/torch.py
dlex/datasets/image/cifar/__init__.py
dlex/datasets/image/cifar/builder.py
dlex/datasets/image/cifar/keras.py
dlex/datasets/image/cifar/torch.py
dlex/datasets/image/mnist/__init__.py
dlex/datasets/image/mnist/builder.py
dlex/datasets/image/mnist/torch.py
dlex/datasets/vision/__init__.py
dlex/datasets/vision/base.py
dlex/datasets/vision/cifar10.py
dlex/datasets/vision/imagenet.py
dlex/datasets/vision/mnist.py
dlex/models/__init__.py
dlex/models/attention2.py
dlex/models/base.py
dlex/models/ctc.py
dlex/models/attention/__init__.py
dlex/models/attention/attention.py
dlex/models/attention/decoder.py
dlex/models/attention/encoder.py
dlex/tf/__init__.py
dlex/tf/backend_tff.py
dlex/tf/datatypes.py
dlex/tf/evaluate.py
dlex/tf/instance_v1.py
dlex/tf/instance_v2.py
dlex/tf/tff.py
dlex/tf/train.py
dlex/tf/models/__init__.py
dlex/tf/models/attention.py
dlex/tf/models/base.py
dlex/tf/models/base_tff.py
dlex/tf/models/base_v1.py
dlex/tf/models/base_v2.py
dlex/torch/__init__.py
dlex/torch/backend.py
dlex/torch/datatypes.py
dlex/torch/evaluate.py
dlex/torch/infer.py
dlex/torch/prepare_dataset.py
dlex/torch/train.py
dlex/torch/datasets/__init__.py
dlex/torch/datasets/cornell_movie_dialogs_corpus.py
dlex/torch/datasets/sate.py
dlex-0.0.7.dist-info/METADATA
dlex-0.0.7.dist-info/WHEEL
dlex-0.0.7.dist-info/top_level.txt
dlex-0.0.7.dist-info/RECORD
