Metadata-Version: 2.1
Name: dlex
Version: 0.0.7
Summary: Deep learning library for research experiments
Home-page: https://github.com/trungd/dlex
Author: Trung V. Dang
Author-email: trungv.dang@outlook.com
License: UNKNOWN
Platform: UNKNOWN
Classifier: Programming Language :: Python :: 3.6
Classifier: License :: OSI Approved :: MIT License
Classifier: Operating System :: OS Independent
Requires-Python: >=2.6
Requires-Dist: tqdm
Requires-Dist: colorlog
Requires-Dist: numpy
Requires-Dist: scikit-learn
Requires-Dist: pyyaml
